any_iter_to_html_table/LICENSE
any_iter_to_html_table/README.MD
any_iter_to_html_table/__init__.py
any_iter_to_html_table/requirements.txt
any_iter_to_html_table/thirdparty.json
any_iter_to_html_table-0.1.dist-info/LICENSE.rst
any_iter_to_html_table-0.1.dist-info/METADATA
any_iter_to_html_table-0.1.dist-info/WHEEL
any_iter_to_html_table-0.1.dist-info/top_level.txt
any_iter_to_html_table-0.1.dist-info/RECORD
