Metadata-Version: 2.1
Name: any-iter-to-html-table
Version: 0.1
Summary: Convert any nested iterable (json, dict, list, tuple ...) to an HTML table. Design is separated from data.
Home-page: https://github.com/hansalemaos/any_iter_to_html_table
Author: Johannes Fischer
Author-email: <aulasparticularesdealemaosp@gmail.com>
License: MIT
Keywords: json,dict,list,HTML,CSS
Classifier: Development Status :: 4 - Beta
Classifier: Programming Language :: Python :: 3 :: Only
Classifier: Programming Language :: Python :: 3.9
Classifier: Topic :: Scientific/Engineering :: Visualization
Classifier: Topic :: Software Development :: Libraries :: Python Modules
Classifier: Topic :: Text Editors :: Text Processing
Classifier: Topic :: Text Processing :: General
Classifier: Topic :: Text Processing :: Indexing
Classifier: Topic :: Text Processing :: Filters
Classifier: Topic :: Utilities
License-File: LICENSE.rst
Requires-Dist: a-pandas-ex-plode-tool
Requires-Dist: pandas
Requires-Dist: regex
Requires-Dist: requests
Requires-Dist: ujson
